LICENSE
MANIFEST.in
README.md
requirements.txt
setup.cfg
setup.py
tfreplknet/__init__.py
tfreplknet/block.py
tfreplknet/drop.py
tfreplknet/ffn.py
tfreplknet/large.py
tfreplknet/model.py
tfreplknet/pad.py
tfreplknet/prep.py
tfreplknet/stage.py
tfreplknet.egg-info/PKG-INFO
tfreplknet.egg-info/SOURCES.txt
tfreplknet.egg-info/dependency_links.txt
tfreplknet.egg-info/requires.txt
tfreplknet.egg-info/top_level.txt